reloadcmd-0.9.0.data/data/__main__.py
reloadcmd-0.9.0.dist-info/DESCRIPTION.rst
reloadcmd-0.9.0.dist-info/METADATA
reloadcmd-0.9.0.dist-info/RECORD
reloadcmd-0.9.0.dist-info/WHEEL
reloadcmd-0.9.0.dist-info/metadata.json
reloadcmd-0.9.0.dist-info/top_level.txt
src/__init__.py
src/__main__.py
src/executor.py
src/monitor.py
