Metadata-Version: 2.0
Name: reloadcmd
Version: 0.9.0
Summary: Reload command on file changed
Home-page: https://github.com/stroem/python-reloadcmd
Author: Jonathan Strom
Author-email: jonathan.strom@gmail.com
License: MIT License
Platform: UNKNOWN
Classifier: Development Status :: 5 - Production/Stable
Classifier: Environment :: Console
Classifier: Intended Audience :: Developers
Classifier: License :: OSI Approved :: MIT License
Classifier: Operating System :: OS Independent
Classifier: Programming Language :: Python
Classifier: Programming Language :: Python :: 2
Classifier: Programming Language :: Python :: 2.6
Classifier: Programming Language :: Python :: 2.7
Classifier: Programming Language :: Python :: 3
Classifier: Programming Language :: Python :: 3.3
Classifier: Programming Language :: Python :: 3.4
Classifier: Topic :: Terminals
Classifier: Topic :: Utilities
